remo/__init__.py
remo/__version__.py
remo/api.py
remo/cli.py
remo/errors.py
remo/models.py
tests/__init__.py
tests/test_api.py
tests/test_cli.py
tests/test_models.py
tests/utils.py
nature_remo_fork_only_for_hacs_nature_remo-0.3.3.dist-info/LICENSE
nature_remo_fork_only_for_hacs_nature_remo-0.3.3.dist-info/METADATA
nature_remo_fork_only_for_hacs_nature_remo-0.3.3.dist-info/WHEEL
nature_remo_fork_only_for_hacs_nature_remo-0.3.3.dist-info/entry_points.txt
nature_remo_fork_only_for_hacs_nature_remo-0.3.3.dist-info/top_level.txt
nature_remo_fork_only_for_hacs_nature_remo-0.3.3.dist-info/RECORD
