Metadata-Version: 2.1
Name: nature-remo-fork-only-for-hacs-nature-remo
Version: 0.3.3
Summary: Python client for Nature Remo API
Home-page: https://github.com/kkiyama117/nature-remo
Author: Shinya Fujino
Author-email: shf0811@gmail.com
License: MIT
Keywords: Nature Remo
Platform: UNKNOWN
Classifier: Development Status :: 4 - Beta
Classifier: Intended Audience :: Developers
Classifier: License :: OSI Approved :: MIT License
Classifier: Programming Language :: Python
Classifier: Programming Language :: Python :: 3
Classifier: Programming Language :: Python :: 3 :: Only
Classifier: Programming Language :: Python :: 3.8
Classifier: Topic :: Home Automation
Classifier: Topic :: Internet
Requires-Dist: marshmallow (>=3.7.1)
Requires-Dist: requests (>=2.27.0)
Requires-Dist: click (>=7.1.2)
